fb_accountkit.py
fb_accountkit-1.0.2.dist-info/METADATA
fb_accountkit-1.0.2.dist-info/RECORD
fb_accountkit-1.0.2.dist-info/WHEEL
fb_accountkit-1.0.2.dist-info/top_level.txt
