Metadata-Version: 2.1
Name: fb-accountkit
Version: 1.0.2
Summary: Facebook AccountKit module for Server-side implementation. https://developers.facebook.com/docs/accountkit/
Home-page: https://github.com/laminko/fb_accountkit
Author: lmk
Author-email: lminko.lmk@gmail.com
License: MIT
Platform: UNKNOWN
Classifier: License :: OSI Approved :: MIT License
Classifier: Programming Language :: Python
Classifier: Programming Language :: Python :: 3
Classifier: Programming Language :: Python :: 3.5
Classifier: Programming Language :: Python :: Implementation :: CPython
Classifier: Programming Language :: Python :: Implementation :: PyPy
Requires-Python: >=3.5.2
